qt_data_extractor/__init__.py
qt_data_extractor/main.py
qt_data_extractor/mainwindow.py
qt_data_extractor/worker_thread.py
qt_data_extractor/design/__init__.py
qt_data_extractor/design/copy-progress.ui
qt_data_extractor/design/copy-prompt.ui
qt_data_extractor/design/create_connection.py
qt_data_extractor/design/main-window.ui
qt_data_extractor/design/manage-connections.ui
qt_data_extractor/design/pandas_model.py
qt_data_extractor/hooks/hook-qt_data_extractor.py
qt_data_extractor-0.4.5.dist-info/LICENSE.txt
qt_data_extractor-0.4.5.dist-info/METADATA
qt_data_extractor-0.4.5.dist-info/WHEEL
qt_data_extractor-0.4.5.dist-info/entry_points.txt
qt_data_extractor-0.4.5.dist-info/top_level.txt
qt_data_extractor-0.4.5.dist-info/RECORD
