Metadata-Version: 2.1
Name: qt-data-extractor
Version: 0.4.5
Summary: Extract data from industrial historians
Home-page: https://github.com/imubit/qt-data-extractor/
Author: Meir Tseitlin
Author-email: meir@imubit.com
License: LGPLv3
Project-URL: Documentation, https://github.com/imubit/qt-data-extractor/
Project-URL: Source, https://github.com/imubit/qt-data-extractor/
Platform: any
Classifier: Development Status :: 4 - Beta
Classifier: Programming Language :: Python
License-File: LICENSE.txt
Requires-Dist: pandas
Requires-Dist: openpyxl
Requires-Dist: PySide6
Requires-Dist: data-agent >=0.2.0
Requires-Dist: data-agent-osisoft-pi >=0.3.0
Requires-Dist: data-agent-aspen-ip21
Requires-Dist: data-agent-zip
Requires-Dist: importlib-metadata ; python_version < "3.8"
Provides-Extra: testing
Requires-Dist: setuptools ; extra == 'testing'
Requires-Dist: pytest ; extra == 'testing'
Requires-Dist: pytest-cov ; extra == 'testing'
Provides-Extra: winexe
Requires-Dist: pyinstaller ; extra == 'winexe'
